Metadata-Version: 2.1
Name: datetime_nepali
Version: 1.0.0.5
Summary: Datetime module that operates on top of Bikram Sambat Date & Nepal Time.
Home-page: https://github.com/44hukum/datetime-nepali
Author: 44hukum <ghukumgh@gmail.com>
Author-email: ghukumgh@gmail.com
License: MIT
Keywords: nepali,bs,b.s,date,datetime,time,timezone,nepal,bikram,sambat,samvat,nepali-date,nepali-datetime,nepal-time,npt,nepal-timezone
Classifier: Programming Language :: Python :: 3
Classifier: License :: OSI Approved :: MIT License
Classifier: Operating System :: OS Independent
Requires-Python: >=3.5
